LICENSE.md
README.md
setup.cfg
setup.py
biscot/Alignment.py
biscot/Blat.py
biscot/Blat.py~
biscot/Key.py
biscot/Map.py
biscot/Misc.py
biscot/Misc.py~
biscot/__init__.py
biscot/biscot.py
biscot.egg-info/PKG-INFO
biscot.egg-info/SOURCES.txt
biscot.egg-info/dependency_links.txt
biscot.egg-info/entry_points.txt
biscot.egg-info/requires.txt
biscot.egg-info/top_level.txt
biscot/__pycache__/Alignment.cpython-36.pyc
biscot/__pycache__/Blat.cpython-36.pyc
biscot/__pycache__/Key.cpython-36.pyc
biscot/__pycache__/Map.cpython-36.pyc
biscot/__pycache__/Misc.cpython-36.pyc
biscot/__pycache__/__init__.cpython-36.pyc
biscot/__pycache__/biscot.cpython-36.pyc
docs/Makefile
docs/biscot.rst
docs/make.bat
docs/modules.rst
docs/build/doctrees/Alignment.doctree
docs/build/doctrees/Alignment_class.doctree
docs/build/doctrees/Alignment_methods.doctree
docs/build/doctrees/Blat.doctree
docs/build/doctrees/Key.doctree
docs/build/doctrees/Map.doctree
docs/build/doctrees/Map_class.doctree
docs/build/doctrees/Map_methods.doctree
docs/build/doctrees/Misc.doctree
docs/build/doctrees/environment.pickle
docs/build/doctrees/index.doctree
docs/build/html/.buildinfo
docs/build/html/Alignment.html
docs/build/html/Alignment_class.html
docs/build/html/Alignment_methods.html
docs/build/html/Blat.html
docs/build/html/Key.html
docs/build/html/Map.html
docs/build/html/Map_class.html
docs/build/html/Map_methods.html
docs/build/html/Misc.html
docs/build/html/genindex.html
docs/build/html/index.html
docs/build/html/objects.inv
docs/build/html/py-modindex.html
docs/build/html/search.html
docs/build/html/searchindex.js
docs/build/html/_modules/index.html
docs/build/html/_modules/biscot/Alignment.html
docs/build/html/_modules/biscot/Blat.html
docs/build/html/_modules/biscot/Key.html
docs/build/html/_modules/biscot/Map.html
docs/build/html/_modules/biscot/Misc.html
docs/build/html/_sources/Alignment.rst.txt
docs/build/html/_sources/Alignment_class.rst.txt
docs/build/html/_sources/Alignment_methods.rst.txt
docs/build/html/_sources/Blat.rst.txt
docs/build/html/_sources/Key.rst.txt
docs/build/html/_sources/Map.rst.txt
docs/build/html/_sources/Map_class.rst.txt
