Metadata-Version: 2.1
Name: biscot
Version: 2.3.3
Summary: Bionano SCaffolding Correction Tool
Home-page: https://github.com/institut-de-genomique/biscot
Author: Benjamin Istace, Caroline Belser, Jean-Marc Aury
Author-email: bistace@genoscope.cns.fr
License: CeCILL
Download-URL: https://github.com/institut-de-genomique/biscot/archive/v2.3.3.tar.gz
Keywords: Genome,Scaffolding,Bionano
Platform: UNKNOWN
Classifier: Development Status :: 4 - Beta
Classifier: Intended Audience :: Science/Research
Classifier: Topic :: Scientific/Engineering :: Bio-Informatics
Classifier: License :: OSI Approved :: CEA CNRS Inria Logiciel Libre License, version 2.1 (CeCILL-2.1)
Classifier: Programming Language :: Python :: 3.6
